ak47/__init__.py
ak47/app.py
ak4777-0.0.2.dist-info/LICENSE
ak4777-0.0.2.dist-info/METADATA
ak4777-0.0.2.dist-info/WHEEL
ak4777-0.0.2.dist-info/top_level.txt
ak4777-0.0.2.dist-info/RECORD
