Metadata-Version: 2.1
Name: ak4777
Version: 0.0.2
Summary: common
Home-page: https://github.com/whdevlab/ak47
Author: WHDevLab
Author-email: whdevlab@163.com
License: MIT
Platform: UNKNOWN
Requires-Dist: requests
Requires-Dist: PyJWT
Requires-Dist: pyDes
